<skin version="1.1"><bkgd_main showhide="show" bkgd_alpha="100" bkgd_color="ABAAAA" imageURL="skin_porchtech_bkgd.jpg" height="300" width="416" y="35" x="176" style="custom" objectType="mc" helpTag="main background" /><visualDisplay showhide="hide" outline_alpha="undefined" outline_color="undefined" bkgd_alpha="100" bkgd_color="CCD5B1" height="125.05" width="125" y="420.75" x="863.35" objectType="mc" helpTag="cover art holder" /><bkgd_info showhide="hide" outline_alpha="undefined" outline_color="undefined" bkgd_alpha="100" bkgd_color="CCD5B1" height="20.05" width="232.35" y="420.75" x="863.35" objectType="mc" helpTag="info background" /><bkgd_pl showhide="hide" outline_alpha="undefined" outline_color="undefined" bkgd_alpha="100" bkgd_color="CCD5B1" height="71.65" width="161.8" y="420.75" x="863.35" objectType="mc" helpTag="playlist background" /><thinker showhide="show" bkgd_alpha="100" bkgd_color="FFFFFF" style="blades" height="20" width="25" y="247" x="185" objectType="mc" helpTag="loading indicator" /><listPlayOpen showhide="show" totalitems="5" pl_t_color_norm_alpha="100" pl_t_color_playing_alpha="100" pl_bg_color_norm_alpha="0" pl_bg_color_playing_alpha="100" pl_bg_color_over_alpha="100" pl_t_color_norm="000000" pl_t_color_playing="FFFFFF" pl_bg_color_norm="000400" pl_bg_color_playing="5E79E2" pl_bg_color_over="BECCC6" height="102" width="183.55" y="179" x="340" objectType="pl" helpTag="click to play / open" /><toggleRandomMC showhide="show" icon_on_alpha="100" icon_on_color="0000E6" icon_alpha="49.609375" icon_color="000000" button_alpha="undefined" button_color="undefined" bkgd_alpha="56.25" bkgd_color="FFFFFF" imageURL="undefined" height="20.1" width="20.15" y="70" x="242.5" style="metal" objectType="mc" helpTag="random playback" /><toggleRepeatMC showhide="show" icon_on_alpha="100" icon_on_color="0000E6" icon_alpha="49.609375" icon_color="000000" button_alpha="undefined" button_color="undefined" bkgd_alpha="56.25" bkgd_color="FFFFFF" imageURL="undefined" height="20.1" width="20.15" y="75" x="272" style="metal" objectType="mc" helpTag="repeat track" /><toggleInfoMC showhide="show" icon_on_alpha="100" icon_on_color="0000E6" icon_alpha="27.34375" icon_color="000000" button_alpha="undefined" button_color="undefined" bkgd_alpha="56.25" bkgd_color="FFFFFF" imageURL="undefined" height="20.1" width="20.15" y="75" x="214" style="metal" objectType="mc" helpTag="help" /><toggleMuteMC showhide="show" icon_on_alpha="88.28125" icon_on_color="FF4800" icon_alpha="40.234375" icon_color="FFFFFF" imageURL="undefined" height="20" width="19.5" y="281" x="297" objectType="mc" helpTag="mute volume" /><playControl_prev showhide="show" icon_alpha="60.546875" icon_color="000000" button_alpha="undefined" button_color="undefined" bkgd_alpha="100" bkgd_color="FFFFFF" imageURL="undefined" height="19.1" width="20.15" y="160" x="208" style="metal" objectType="mc" helpTag="previous track" /><playControl_pause showhide="hide" icon_alpha="60.546875" icon_color="000000" button_alpha="undefined" button_color="undefined" bkgd_alpha="100" bkgd_color="FFFFFF" imageURL="undefined" height="33.1" width="33.3" y="420.75" x="863.35" style="metal" objectType="mc" helpTag="pause" /><playControl_next showhide="show" icon_alpha="60.546875" icon_color="000000" button_alpha="undefined" button_color="undefined" bkgd_alpha="100" bkgd_color="FFFFFF" imageURL="undefined" height="19.1" width="20.15" y="159" x="277" style="metal" objectType="mc" helpTag="next track" /><playControl_play showhide="show" icon_alpha="60.546875" icon_color="000000" button_alpha="undefined" button_color="undefined" bkgd_alpha="100" bkgd_color="FFFFFF" imageURL="undefined" height="33.1" width="33.3" y="157" x="236" style="metal" objectType="mc" helpTag="play track" /><scrub_line showhide="show" outline_alpha="75.390625" outline_color="undefined" loader_alpha="67.578125" loader_color="1B4A43" bkgd_alpha="31.640625" bkgd_color="FFFFFF" imageURL="undefined" height="3.15" width="242.5" y="143" x="326" style="bevel" objectType="scrub" helpTag="position locator" /><scrubber showhide="show" button_alpha="100" button_color="undefined" bkgd_alpha="100" bkgd_color="FFFFFF" imageURL="undefined" height="14" width="14.95" y="137.55" x="326" style="glass" objectType="scrub" helpTag="location handle" /><playlist_back showhide="show" icon_alpha="60.546875" icon_color="000000" button_alpha="undefined" button_color="undefined" bkgd_alpha="100" bkgd_color="FFFFFF" imageURL="undefined" height="19" width="19" y="199" x="295" style="metal" objectType="mc" helpTag="previous playlist" /><playlist_line showhide="show" outline_alpha="75.390625" outline_color="undefined" bkgd_alpha="31.640625" bkgd_color="FFFFFF" height="60" width="4.75" y="199" x="545" style="bevel" objectType="pl_scroll" helpTag="scroll playlist one page" /><playlist_handle showhide="show" button_alpha="undefined" button_color="undefined" bkgd_alpha="100" bkgd_color="FFFFFF" imageURL="undefined" height="16.05" width="15.95" y="199" x="539.4" style="glass" objectType="pl_scroll" helpTag="scroll playlist" /><vol_line showhide="show" outline_alpha="75.390625" outline_color="undefined" bkgd_alpha="31.640625" bkgd_color="FFFFFF" height="48.2" width="10" y="228" x="300" style="bevel" rotation="-90" objectType="vol" helpTag="set volume" /><vol_handle showhide="show" button_alpha="undefined" button_color="undefined" bkgd_alpha="100" bkgd_color="B6BABA" imageURL="undefined" height="12" width="9.35" y="228" x="300.3" style="fade" objectType="vol" helpTag="adjust volume" /><itext showhide="show" color="000000" height="16" width="235" y="115" x="329" objectType="itext" helpTag="track info" /><itime showhide="show" color="000006" height="25" width="78" y="102" x="210" objectType="itime" helpTag="track time" /><startUpText showhide="show" theText="Click an item to start playing a track" /><fakeEQ showhide="show" alpha="37.890625" color="000056" height="13" width="61" y="133" x="223" totalBars="14" objectType="mc" /><toggleVoteMC showhide="hide" icon_on_alpha="100" icon_on_color="0000E6" icon_alpha="49.609375" icon_color="A80000" button_alpha="100" button_color="000000" bkgd_alpha="56.25" bkgd_color="FFFFFF" imageURL="undefined" height="14" width="14" y="420.75" x="863.35" style="bevel" objectType="mc" helpTag="Vote for this track" /><playlistScrollerUp showhide="show" icon_alpha="60.546875" icon_color="000000" button_alpha="undefined" button_color="undefined" bkgd_alpha="100" bkgd_color="FFFFFF" imageURL="undefined" height="15" width="15" y="177" x="539" style="metal" objectType="mc" helpTag="Scroll playlist up" /><playlistScrollerDown showhide="show" icon_alpha="60.546875" icon_color="000000" button_alpha="undefined" button_color="undefined" bkgd_alpha="100" bkgd_color="FFFFFF" imageURL="undefined" height="15" width="15" y="266" x="539" style="metal" objectType="mc" helpTag="Scrol playlist down" /></skin>